xportage/__init__.py
xportage/__main__.py
xportage/default_reference.py
xportage/xportage.py
xportage/reading/__init__.py
xportage/reading/reader.py
xportage/reading_raw/__init__.py
xportage/reading_raw/get_reader.py
xportage/reading_raw/reader.py
xportage/reading_raw/sst.py
xportage/utils/__init__.py
xportage/utils/tree.py
xportage-0.0.3.dist-info/METADATA
xportage-0.0.3.dist-info/RECORD
xportage-0.0.3.dist-info/WHEEL
xportage-0.0.3.dist-info/entry_points.txt
xportage-0.0.3.dist-info/top_level.txt
