Metadata-Version: 2.1
Name: xportage
Version: 0.0.3
Summary: Makes reading data easy.
Home-page: https://github.com/mrdrozdov/xportage
Author: Andrew Drozdov
Author-email: andrew@mrdrozdov.com
License: MIT
Platform: UNKNOWN
Classifier: License :: OSI Approved :: MIT License
Classifier: Programming Language :: Python :: 3
Classifier: Programming Language :: Python :: 3.7
Requires-Dist: nltk
